omnium/__init__.py
omnium/analyser.py
omnium/analyser_setting.py
omnium/analysers.py
omnium/analyzer.py
omnium/analyzers.py
omnium/bcolors.py
omnium/command_parser.py
omnium/consts.py
omnium/converter.py
omnium/converters.py
omnium/deleter.py
omnium/mpi_control.py
omnium/omnium_cmd.py
omnium/omnium_errors.py
omnium/omnium_state.py
omnium/pkg_state.py
omnium/run_control.py
omnium/setup_logging.py
omnium/stash.py
omnium/state.py
omnium/suite.py
omnium/syncher.py
omnium/task.py
omnium/threed_viewer.py
omnium/twod_viewer.py
omnium/utils.py
omnium/version.py
omnium/analysis/__init__.py
omnium/analysis/analyser.py
omnium/analysis/analysis_pkgs.py
omnium/analysis/analysis_settings.py
omnium/analysis/converter.py
omnium/analysis/deleter.py
omnium/cmds/__init__.py
omnium/cmds/analyser_info.py
omnium/cmds/cat_log.py
omnium/cmds/clean_symlinks.py
omnium/cmds/cmd_context.py
omnium/cmds/convert.py
omnium/cmds/expt_info.py
omnium/cmds/fetch.py
omnium/cmds/file_cat.py
omnium/cmds/file_info.py
omnium/cmds/ls_analysers.py
omnium/cmds/ls_analyzers.py
omnium/cmds/remote_cmd.py
omnium/cmds/run.py
omnium/cmds/send.py
omnium/cmds/shell.py
omnium/cmds/stash.py
omnium/cmds/suite_clone.py
omnium/cmds/suite_freeze.py
omnium/cmds/suite_info.py
omnium/cmds/suite_init.py
omnium/cmds/suite_unfreeze.py
omnium/cmds/sync.py
omnium/cmds/sync_mirror.py
omnium/cmds/test.py
omnium/cmds/threed_viewer.py
omnium/cmds/version.py
omnium/cmds/viewer.py
omnium/data/__init__.py
omnium/data/files/vn10.5/STASHmaster-meta.conf
omnium/data/files/vn10.5/STASHmaster_A
omnium/omnium_cmds/__init__.py
omnium/omnium_cmds/convert.py
omnium/omnium_cmds/stash.py
omnium/omnium_cmds/threed_viewer.py
omnium/omnium_cmds/version.py
omnium/omnium_cmds/viewer.py
omnium/run_control/__init__.py
omnium/run_control/mpi_control.py
omnium/run_control/run_control.py
omnium/run_control/task.py
omnium/suite/__init__.py
omnium/suite/expt.py
omnium/suite/suite.py
omnium-0.10.3.dist-info/DESCRIPTION.rst
omnium-0.10.3.dist-info/METADATA
omnium-0.10.3.dist-info/RECORD
omnium-0.10.3.dist-info/WHEEL
omnium-0.10.3.dist-info/metadata.json
omnium-0.10.3.dist-info/top_level.txt
