Metadata-Version: 2.0
Name: omnium
Version: 0.10.3
Summary: Output Management with Natural Interface for the UM
Home-page: https://github.com/markmuetz/omnium
Author: Mark Muetzelfeldt
Author-email: m.muetzelfeldt@pgr.reading.ac.uk
License: UNKNOWN
Platform: UNKNOWN
Classifier: Environment :: Console
Classifier: Intended Audience :: Science/Research
Classifier: Natural Language :: English
Classifier: Operating System :: POSIX :: Linux
Classifier: Programming Language :: Python :: 3.6
Classifier: Topic :: Scientific/Engineering :: Atmospheric Science
Requires-Python: >=3.6
Requires-Dist: configparser
Requires-Dist: iris
Requires-Dist: mock
Requires-Dist: nose
Requires-Dist: numpy
Requires-Dist: simplejson
Provides-Extra: viewer
Requires-Dist: pyopengl; extra == 'viewer'
Requires-Dist: pyqtgraph; extra == 'viewer'
